alethe/__init__.py
alethe/alethe.py
alethe/llm.py
alethe/prompts.py
alethe/semantic_diff.py
alethe-0.1.0.dist-info/licenses/LICENSE
alethe-0.1.0.dist-info/METADATA
alethe-0.1.0.dist-info/WHEEL
alethe-0.1.0.dist-info/top_level.txt
alethe-0.1.0.dist-info/RECORD
