Metadata-Version: 2.4
Name: alethe
Version: 0.1.0
Summary: AI-powered code explainer and semantic diff tool
Home-page: https://github.com/lilscolari/alethe
Author: Cameron Scolari
Author-email: cameronscolari@outlook.com
License: MIT
Classifier: Development Status :: 4 - Beta
Classifier: Intended Audience :: Developers
Classifier: License :: OSI Approved :: MIT License
Classifier: Programming Language :: Python :: 3
Classifier: Programming Language :: Python :: 3.10
Classifier: Topic :: Software Development :: Code Generators
Requires-Python: >=3.10
License-File: LICENSE
Requires-Dist: transformers
Requires-Dist: torch
Provides-Extra: dev
Requires-Dist: black; extra == "dev"
Requires-Dist: flake8; extra == "dev"
Requires-Dist: isort; extra == "dev"
Dynamic: license-file
